[
  {
    "epoch": 1,
    "train_loss": 1.146422951065637,
    "accuracy": 0.9304453935326419,
    "macro_f1": 0.5288671423577186,
    "weighted_f1": 0.945720996289001,
    "non_transition_f1": 0.9727422003284072,
    "direction_macro_f1": 0.4548879660292704,
    "worst_direction_f1": 0.0,
    "transition_precision": 0.4807692307692308,
    "transition_recall": 0.974025974025974,
    "transition_f1": 0.6437768240343348,
    "per_class_f1": [
      0.9727422003284072,
      0.6363636363636364,
      0.8,
      0.4375,
      0.0,
      0.2608695652173913,
      0.5945945945945946
    ],
    "confusion_matrix": [
      [
        1481,
        3,
        0,
        4,
        4,
        67,
        3
      ],
      [
        2,
        7,
        0,
        0,
        0,
        2,
        0
      ],
      [
        0,
        1,
        4,
        0,
        0,
        0,
        0
      ],
      [
        0,
        0,
        0,
        7,
        0,
        9,
        0
      ],
      [
        0,
        0,
        0,
        0,
        0,
        1,
        11
      ],
      [
        0,
        0,
        1,
        5,
        0,
        15,
        0
      ],
      [
        0,
        0,
        0,
        0,
        1,
        0,
        11
      ]
    ],
    "loss": 0.8010879244434899
  },
  {
    "epoch": 2,
    "train_loss": 0.7695716788410362,
    "accuracy": 0.896888346552776,
    "macro_f1": 0.47723143602865636,
    "weighted_f1": 0.9255036292146152,
    "non_transition_f1": 0.9521579123452659,
    "direction_macro_f1": 0.3980770233092214,
    "worst_direction_f1": 0.17777777777777778,
    "transition_precision": 0.3443396226415094,
    "transition_recall": 0.948051948051948,
    "transition_f1": 0.5051903114186851,
    "per_class_f1": [
      0.9521579123452659,
      0.2727272727272727,
      0.6153846153846154,
      0.3235294117647059,
      0.5263157894736842,
      0.4727272727272727,
      0.17777777777777778
    ],
    "confusion_matrix": [
      [
        1423,
        27,
        0,
        34,
        0,
        13,
        65
      ],
      [
        2,
        6,
        1,
        0,
        0,
        2,
        0
      ],
      [
        1,
        0,
        4,
        0,
        0,
        0,
        0
      ],
      [
        0,
        0,
        0,
        11,
        0,
        5,
        0
      ],
      [
        0,
        0,
        1,
        0,
        5,
        1,
        5
      ],
      [
        0,
        0,
        1,
        7,
        0,
        13,
        0
      ],
      [
        1,
        0,
        1,
        0,
        2,
        0,
        8
      ]
    ],
    "loss": 0.7822341791844499
  },
  {
    "epoch": 3,
    "train_loss": 0.6291072930366385,
    "accuracy": 0.9572910311165345,
    "macro_f1": 0.5543366542752098,
    "weighted_f1": 0.9634999689871295,
    "non_transition_f1": 0.9860434923726062,
    "direction_macro_f1": 0.4823855145923104,
    "worst_direction_f1": 0.2857142857142857,
    "transition_precision": 0.6416666666666667,
    "transition_recall": 1.0,
    "transition_f1": 0.7817258883248731,
    "per_class_f1": [
      0.9860434923726062,
      0.5,
      0.43478260869565216,
      0.6470588235294118,
      0.2857142857142857,
      0.5777777777777777,
      0.4489795918367347
    ],
    "confusion_matrix": [
      [
        1519,
        13,
        9,
        1,
        0,
        5,
        15
      ],
      [
        0,
        8,
        1,
        0,
        0,
        1,
        1
      ],
      [
        0,
        0,
        5,
        0,
        0,
        0,
        0
      ],
      [
        0,
        0,
        0,
        11,
        0,
        5,
        0
      ],
      [
        0,
        0,
        0,
        0,
        2,
        0,
        10
      ],
      [
        0,
        0,
        2,
        6,
        0,
        13,
        0
      ],
      [
        0,
        0,
        1,
        0,
        0,
        0,
        11
      ]
    ],
    "loss": 0.6522981834037046
  },
  {
    "epoch": 4,
    "train_loss": 0.48155213514379425,
    "accuracy": 0.9676632092739476,
    "macro_f1": 0.6815615110001012,
    "weighted_f1": 0.971591005518381,
    "non_transition_f1": 0.9899773682508891,
    "direction_macro_f1": 0.6301588681249698,
    "worst_direction_f1": 0.5084745762711864,
    "transition_precision": 0.7129629629629629,
    "transition_recall": 1.0,
    "transition_f1": 0.8324324324324325,
    "per_class_f1": [
      0.9899773682508891,
      0.6923076923076923,
      0.7692307692307693,
      0.5555555555555556,
      0.64,
      0.5084745762711864,
      0.6153846153846154
    ],
    "confusion_matrix": [
      [
        1531,
        6,
        2,
        5,
        1,
        15,
        2
      ],
      [
        0,
        9,
        0,
        0,
        0,
        2,
        0
      ],
      [
        0,
        0,
        5,
        0,
        0,
        0,
        0
      ],
      [
        0,
        0,
        0,
        10,
        0,
        6,
        0
      ],
      [
        0,
        0,
        0,
        0,
        8,
        0,
        4
      ],
      [
        0,
        0,
        1,
        5,
        0,
        15,
        0
      ],
      [
        0,
        0,
        0,
        0,
        4,
        0,
        8
      ]
    ],
    "loss": 0.5792932087797592
  },
  {
    "epoch": 5,
    "train_loss": 0.45503095269203186,
    "accuracy": 0.9017693715680293,
    "macro_f1": 0.5960163488895767,
    "weighted_f1": 0.9322458658161867,
    "non_transition_f1": 0.9534338358458961,
    "direction_macro_f1": 0.5364467677301902,
    "worst_direction_f1": 0.1487603305785124,
    "transition_precision": 0.35648148148148145,
    "transition_recall": 1.0,
    "transition_f1": 0.5255972696245734,
    "per_class_f1": [
      0.9534338358458961,
      0.1487603305785124,
      0.8333333333333334,
      0.5882352941176471,
      0.6666666666666666,
      0.41025641025641024,
      0.5714285714285714
    ],
    "confusion_matrix": [
      [
        1423,
        101,
        1,
        3,
        0,
        33,
        1
      ],
      [
        0,
        9,
        0,
        0,
        0,
        2,
        0
      ],
      [
        0,
        0,
        5,
        0,
        0,
        0,
        0
      ],
      [
        0,
        0,
        0,
        10,
        0,
        6,
        0
      ],
      [
        0,
        0,
        0,
        1,
        9,
        0,
        2
      ],
      [
        0,
        0,
        1,
        4,
        0,
        16,
        0
      ],
      [
        0,
        0,
        0,
        0,
        6,
        0,
        6
      ]
    ],
    "loss": 0.5380399554531483
  },
  {
    "epoch": 6,
    "train_loss": 0.4263779010764914,
    "accuracy": 0.9572910311165345,
    "macro_f1": 0.6563417872825539,
    "weighted_f1": 0.9644769957194249,
    "non_transition_f1": 0.9840650406504065,
    "direction_macro_f1": 0.6017212450545784,
    "worst_direction_f1": 0.4864864864864865,
    "transition_precision": 0.6111111111111112,
    "transition_recall": 1.0,
    "transition_f1": 0.7586206896551724,
    "per_class_f1": [
      0.9840650406504065,
      0.4864864864864865,
      0.8333333333333334,
      0.5714285714285714,
      0.64,
      0.4864864864864865,
      0.5925925925925926
    ],
    "confusion_matrix": [
      [
        1513,
        17,
        0,
        2,
        2,
        25,
        3
      ],
      [
        0,
        9,
        0,
        0,
        0,
        2,
        0
      ],
      [
        0,
        0,
        5,
        0,
        0,
        0,
        0
      ],
      [
        0,
        0,
        0,
        8,
        0,
        8,
        0
      ],
      [
        0,
        0,
        0,
        0,
        8,
        0,
        4
      ],
      [
        0,
        0,
        1,
        2,
        0,
        18,
        0
      ],
      [
        0,
        0,
        1,
        0,
        3,
        0,
        8
      ]
    ],
    "loss": 0.5401328429988858
  },
  {
    "epoch": 7,
    "train_loss": 0.3512763470635305,
    "accuracy": 0.975594874923734,
    "macro_f1": 0.728552884987577,
    "weighted_f1": 0.9783234703899746,
    "non_transition_f1": 0.9929078014184397,
    "direction_macro_f1": 0.6844937322490998,
    "worst_direction_f1": 0.5142857142857142,
    "transition_precision": 0.7777777777777778,
    "transition_recall": 1.0,
    "transition_f1": 0.875,
    "per_class_f1": [
      0.9929078014184397,
      0.5142857142857142,
      0.7272727272727273,
      0.6896551724137931,
      0.7272727272727273,
      0.6792452830188679,
      0.7692307692307693
    ],
    "confusion_matrix": [
      [
        1540,
        13,
        1,
        1,
        0,
        6,
        1
      ],
      [
        0,
        9,
        0,
        0,
        0,
        2,
        0
      ],
      [
        0,
        1,
        4,
        0,
        0,
        0,
        0
      ],
      [
        0,
        0,
        0,
        10,
        0,
        6,
        0
      ],
      [
        0,
        1,
        0,
        0,
        8,
        0,
        3
      ],
      [
        0,
        0,
        1,
        2,
        0,
        18,
        0
      ],
      [
        0,
        0,
        0,
        0,
        2,
        0,
        10
      ]
    ],
    "loss": 0.5271104306228064
  },
  {
    "epoch": 8,
    "train_loss": 0.3610427568570461,
    "accuracy": 0.975594874923734,
    "macro_f1": 0.7247177945502371,
    "weighted_f1": 0.9772972035420902,
    "non_transition_f1": 0.9938808373590983,
    "direction_macro_f1": 0.6798572874154268,
    "worst_direction_f1": 0.5116279069767442,
    "transition_precision": 0.8020833333333334,
    "transition_recall": 1.0,
    "transition_f1": 0.8901734104046243,
    "per_class_f1": [
      0.9938808373590983,
      0.7142857142857143,
      0.9090909090909091,
      0.717948717948718,
      0.6428571428571429,
      0.5116279069767442,
      0.5833333333333334
    ],
    "confusion_matrix": [
      [
        1543,
        5,
        0,
        2,
        2,
        8,
        2
      ],
      [
        0,
        10,
        0,
        0,
        0,
        1,
        0
      ],
      [
        0,
        0,
        5,
        0,
        0,
        0,
        0
      ],
      [
        0,
        0,
        0,
        14,
        0,
        2,
        0
      ],
      [
        0,
        0,
        0,
        0,
        9,
        0,
        3
      ],
      [
        0,
        2,
        1,
        7,
        0,
        11,
        0
      ],
      [
        0,
        0,
        0,
        0,
        5,
        0,
        7
      ]
    ],
    "loss": 0.5191163735338069
  },
  {
    "epoch": 9,
    "train_loss": 0.28375988908063354,
    "accuracy": 0.9859670530811471,
    "macro_f1": 0.8186509957540979,
    "weighted_f1": 0.9864385584758505,
    "non_transition_f1": 0.9977542508822586,
    "direction_macro_f1": 0.7888004532327377,
    "worst_direction_f1": 0.6511627906976745,
    "transition_precision": 0.9166666666666666,
    "transition_recall": 1.0,
    "transition_f1": 0.9565217391304348,
    "per_class_f1": [
      0.9977542508822586,
      0.8333333333333334,
      0.9090909090909091,
      0.7058823529411765,
      0.8333333333333334,
      0.6511627906976745,
      0.8
    ],
    "confusion_matrix": [
      [
        1555,
        2,
        0,
        1,
        0,
        3,
        1
      ],
      [
        0,
        10,
        0,
        0,
        0,
        1,
        0
      ],
      [
        0,
        0,
        5,
        0,
        0,
        0,
        0
      ],
      [
        0,
        0,
        0,
        12,
        0,
        4,
        0
      ],
      [
        0,
        0,
        0,
        0,
        10,
        0,
        2
      ],
      [
        0,
        1,
        1,
        5,
        0,
        14,
        0
      ],
      [
        0,
        0,
        0,
        0,
        2,
        0,
        10
      ]
    ],
    "loss": 0.44678279988426783
  },
  {
    "epoch": 10,
    "train_loss": 0.26550788159415223,
    "accuracy": 0.9731543624161074,
    "macro_f1": 0.6858479343122018,
    "weighted_f1": 0.9751404603263609,
    "non_transition_f1": 0.9929078014184397,
    "direction_macro_f1": 0.6346712897944955,
    "worst_direction_f1": 0.47058823529411764,
    "transition_precision": 0.7777777777777778,
    "transition_recall": 1.0,
    "transition_f1": 0.875,
    "per_class_f1": [
      0.9929078014184397,
      0.625,
      0.8,
      0.5925925925925926,
      0.47058823529411764,
      0.6101694915254238,
      0.7096774193548387
    ],
    "confusion_matrix": [
      [
        1540,
        7,
        0,
        2,
        0,
        11,
        2
      ],
      [
        0,
        10,
        0,
        0,
        0,
        1,
        0
      ],
      [
        0,
        1,
        4,
        0,
        0,
        0,
        0
      ],
      [
        0,
        0,
        0,
        8,
        0,
        8,
        0
      ],
      [
        0,
        2,
        0,
        0,
        4,
        0,
        6
      ],
      [
        0,
        1,
        1,
        1,
        0,
        18,
        0
      ],
      [
        0,
        0,
        0,
        0,
        1,
        0,
        11
      ]
    ],
    "loss": 0.5587380561361668
  },
  {
    "epoch": 11,
    "train_loss": 0.289807551179836,
    "accuracy": 0.971934106162294,
    "macro_f1": 0.7626801769658912,
    "weighted_f1": 0.9757163555677714,
    "non_transition_f1": 0.9903038138332256,
    "direction_macro_f1": 0.7247429041546688,
    "worst_direction_f1": 0.5230769230769231,
    "transition_precision": 0.719626168224299,
    "transition_recall": 1.0,
    "transition_f1": 0.8369565217391305,
    "per_class_f1": [
      0.9903038138332256,
      0.7692307692307693,
      0.9090909090909091,
      0.6470588235294118,
      0.75,
      0.5230769230769231,
      0.75
    ],
    "confusion_matrix": [
      [
        1532,
        5,
        0,
        3,
        0,
        21,
        1
      ],
      [
        0,
        10,
        0,
        0,
        0,
        1,
        0
      ],
      [
        0,
        0,
        5,
        0,
        0,
        0,
        0
      ],
      [
        0,
        0,
        0,
        11,
        0,
        5,
        0
      ],
      [
        0,
        0,
        0,
        1,
        9,
        0,
        2
      ],
      [
        0,
        0,
        1,
        3,
        0,
        17,
        0
      ],
      [
        0,
        0,
        0,
        0,
        3,
        0,
        9
      ]
    ],
    "loss": 0.5093909992976767
  },
  {
    "epoch": 12,
    "train_loss": 0.2704657638394365,
    "accuracy": 0.9347162904209884,
    "macro_f1": 0.6941223375132862,
    "weighted_f1": 0.9519286071969849,
    "non_transition_f1": 0.9706754530477759,
    "direction_macro_f1": 0.6480301515908712,
    "worst_direction_f1": 0.27586206896551724,
    "transition_precision": 0.463855421686747,
    "transition_recall": 1.0,
    "transition_f1": 0.6337448559670782,
    "per_class_f1": [
      0.9706754530477759,
      0.625,
      1.0,
      0.625,
      0.6956521739130435,
      0.27586206896551724,
      0.6666666666666666
    ],
    "confusion_matrix": [
      [
        1473,
        10,
        0,
        3,
        1,
        72,
        3
      ],
      [
        0,
        10,
        0,
        0,
        0,
        1,
        0
      ],
      [
        0,
        0,
        5,
        0,
        0,
        0,
        0
      ],
      [
        0,
        0,
        0,
        10,
        0,
        6,
        0
      ],
      [
        0,
        0,
        0,
        0,
        8,
        0,
        4
      ],
      [
        0,
        1,
        0,
        3,
        0,
        16,
        1
      ],
      [
        0,
        0,
        0,
        0,
        2,
        0,
        10
      ]
    ],
    "loss": 0.500683576593663
  },
  {
    "epoch": 13,
    "train_loss": 0.2687746781773037,
    "accuracy": 0.9847467968273338,
    "macro_f1": 0.812006463876639,
    "weighted_f1": 0.9855423238757818,
    "non_transition_f1": 0.9967886962106616,
    "direction_macro_f1": 0.7812094251543019,
    "worst_direction_f1": 0.6808510638297872,
    "transition_precision": 0.8850574712643678,
    "transition_recall": 1.0,
    "transition_f1": 0.9390243902439024,
    "per_class_f1": [
      0.9967886962106616,
      0.75,
      0.9090909090909091,
      0.7647058823529411,
      0.782608695652174,
      0.6808510638297872,
      0.8
    ],
    "confusion_matrix": [
      [
        1552,
        3,
        0,
        1,
        0,
        5,
        1
      ],
      [
        0,
        9,
        0,
        0,
        0,
        2,
        0
      ],
      [
        0,
        0,
        5,
        0,
        0,
        0,
        0
      ],
      [
        0,
        0,
        0,
        13,
        0,
        3,
        0
      ],
      [
        0,
        1,
        0,
        0,
        9,
        0,
        2
      ],
      [
        0,
        0,
        1,
        4,
        0,
        16,
        0
      ],
      [
        0,
        0,
        0,
        0,
        2,
        0,
        10
      ]
    ],
    "loss": 0.4856448394562901
  },
  {
    "epoch": 14,
    "train_loss": 0.25519552817044694,
    "accuracy": 0.9774252593044539,
    "macro_f1": 0.671073255222488,
    "weighted_f1": 0.9766750326400832,
    "non_transition_f1": 0.9954983922829582,
    "direction_macro_f1": 0.6170023990457427,
    "worst_direction_f1": 0.0,
    "transition_precision": 0.8461538461538461,
    "transition_recall": 1.0,
    "transition_f1": 0.9166666666666666,
    "per_class_f1": [
      0.9954983922829582,
      0.8,
      0.9090909090909091,
      0.7142857142857143,
      0.0,
      0.631578947368421,
      0.6470588235294118
    ],
    "confusion_matrix": [
      [
        1548,
        4,
        0,
        0,
        0,
        9,
        1
      ],
      [
        0,
        10,
        0,
        0,
        0,
        1,
        0
      ],
      [
        0,
        0,
        5,
        0,
        0,
        0,
        0
      ],
      [
        0,
        0,
        0,
        10,
        0,
        6,
        0
      ],
      [
        0,
        0,
        0,
        0,
        0,
        2,
        10
      ],
      [
        0,
        0,
        1,
        2,
        0,
        18,
        0
      ],
      [
        0,
        0,
        0,
        0,
        1,
        0,
        11
      ]
    ],
    "loss": 0.6438087757115433
  },
  {
    "epoch": 15,
    "train_loss": 0.2509805533075644,
    "accuracy": 0.9731543624161074,
    "macro_f1": 0.6678553597263746,
    "weighted_f1": 0.9746681016061808,
    "non_transition_f1": 0.9929078014184397,
    "direction_macro_f1": 0.613679952777697,
    "worst_direction_f1": 0.2857142857142857,
    "transition_precision": 0.7777777777777778,
    "transition_recall": 1.0,
    "transition_f1": 0.875,
    "per_class_f1": [
      0.9929078014184397,
      0.7142857142857143,
      0.8,
      0.7027027027027027,
      0.5263157894736842,
      0.6530612244897959,
      0.2857142857142857
    ],
    "confusion_matrix": [
      [
        1540,
        4,
        0,
        4,
        6,
        8,
        0
      ],
      [
        0,
        10,
        0,
        0,
        0,
        1,
        0
      ],
      [
        0,
        1,
        4,
        0,
        0,
        0,
        0
      ],
      [
        0,
        0,
        0,
        13,
        0,
        3,
        0
      ],
      [
        0,
        2,
        0,
        0,
        10,
        0,
        0
      ],
      [
        0,
        0,
        1,
        4,
        0,
        16,
        0
      ],
      [
        0,
        0,
        0,
        0,
        10,
        0,
        2
      ]
    ],
    "loss": 0.5961973812542469
  },
  {
    "epoch": 16,
    "train_loss": 0.2464098029393776,
    "accuracy": 0.9762050030506406,
    "macro_f1": 0.6922679181082543,
    "weighted_f1": 0.9780005519112939,
    "non_transition_f1": 0.9948519948519948,
    "direction_macro_f1": 0.6418372386509642,
    "worst_direction_f1": 0.5384615384615384,
    "transition_precision": 0.8279569892473119,
    "transition_recall": 1.0,
    "transition_f1": 0.9058823529411765,
    "per_class_f1": [
      0.9948519948519948,
      0.5882352941176471,
      0.625,
      0.7222222222222222,
      0.7407407407407407,
      0.5384615384615384,
      0.6363636363636364
    ],
    "confusion_matrix": [
      [
        1546,
        1,
        1,
        1,
        0,
        12,
        1
      ],
      [
        0,
        5,
        4,
        0,
        0,
        2,
        0
      ],
      [
        0,
        0,
        5,
        0,
        0,
        0,
        0
      ],
      [
        0,
        0,
        0,
        13,
        0,
        3,
        0
      ],
      [
        0,
        0,
        0,
        0,
        10,
        0,
        2
      ],
      [
        0,
        0,
        1,
        6,
        0,
        14,
        0
      ],
      [
        0,
        0,
        0,
        0,
        5,
        0,
        7
      ]
    ],
    "loss": 0.8307543405495889
  },
  {
    "epoch": 17,
    "train_loss": 0.45708417691631253,
    "accuracy": 0.9341061622940817,
    "macro_f1": 0.7348067428803954,
    "weighted_f1": 0.9558947680155331,
    "non_transition_f1": 0.9696569920844327,
    "direction_macro_f1": 0.6956650346797225,
    "worst_direction_f1": 0.19298245614035087,
    "transition_precision": 0.4556213017751479,
    "transition_recall": 1.0,
    "transition_f1": 0.6260162601626016,
    "per_class_f1": [
      0.9696569920844327,
      0.19298245614035087,
      1.0,
      0.7333333333333333,
      0.75,
      0.6976744186046512,
      0.8
    ],
    "confusion_matrix": [
      [
        1470,
        86,
        0,
        0,
        1,
        4,
        1
      ],
      [
        0,
        11,
        0,
        0,
        0,
        0,
        0
      ],
      [
        0,
        0,
        5,
        0,
        0,
        0,
        0
      ],
      [
        0,
        2,
        0,
        11,
        0,
        3,
        0
      ],
      [
        0,
        1,
        0,
        0,
        9,
        0,
        2
      ],
      [
        0,
        3,
        0,
        3,
        0,
        15,
        0
      ],
      [
        0,
        0,
        0,
        0,
        2,
        0,
        10
      ]
    ],
    "loss": 0.4942761780131583
  },
  {
    "epoch": 18,
    "train_loss": 0.2513604078339595,
    "accuracy": 0.9810860280658938,
    "macro_f1": 0.7836258199255858,
    "weighted_f1": 0.9824498184088993,
    "non_transition_f1": 0.9958212793314047,
    "direction_macro_f1": 0.748259910024616,
    "worst_direction_f1": 0.6274509803921569,
    "transition_precision": 0.8555555555555555,
    "transition_recall": 1.0,
    "transition_f1": 0.9221556886227545,
    "per_class_f1": [
      0.9958212793314047,
      0.8181818181818182,
      1.0,
      0.7647058823529411,
      0.6363636363636364,
      0.6274509803921569,
      0.6428571428571429
    ],
    "confusion_matrix": [
      [
        1549,
        2,
        0,
        0,
        0,
        10,
        1
      ],
      [
        0,
        9,
        0,
        0,
        0,
        1,
        1
      ],
      [
        0,
        0,
        5,
        0,
        0,
        0,
        0
      ],
      [
        0,
        0,
        0,
        13,
        0,
        3,
        0
      ],
      [
        0,
        0,
        0,
        0,
        7,
        0,
        5
      ],
      [
        0,
        0,
        0,
        5,
        0,
        16,
        0
      ],
      [
        0,
        0,
        0,
        0,
        3,
        0,
        9
      ]
    ],
    "loss": 0.4817842383089954
  },
  {
    "epoch": 19,
    "train_loss": 0.2041209307936282,
    "accuracy": 0.9438682123245882,
    "macro_f1": 0.6862572741399673,
    "weighted_f1": 0.9577200006071118,
    "non_transition_f1": 0.9743926460932371,
    "direction_macro_f1": 0.6382347121477556,
    "worst_direction_f1": 0.2727272727272727,
    "transition_precision": 0.4967741935483871,
    "transition_recall": 1.0,
    "transition_f1": 0.6637931034482759,
    "per_class_f1": [
      0.9743926460932371,
      0.2727272727272727,
      0.7692307692307693,
      0.7428571428571429,
      0.7692307692307693,
      0.4927536231884058,
      0.782608695652174
    ],
    "confusion_matrix": [
      [
        1484,
        46,
        1,
        3,
        1,
        27,
        0
      ],
      [
        0,
        9,
        1,
        0,
        0,
        1,
        0
      ],
      [
        0,
        0,
        5,
        0,
        0,
        0,
        0
      ],
      [
        0,
        0,
        0,
        13,
        0,
        3,
        0
      ],
      [
        0,
        0,
        0,
        0,
        10,
        0,
        2
      ],
      [
        0,
        0,
        1,
        3,
        0,
        17,
        0
      ],
      [
        0,
        0,
        0,
        0,
        3,
        0,
        9
      ]
    ],
    "loss": 0.5254740764803462
  }
]